odoo8_addon_logistic_requisition_multicurrency-8.0.0.1.1-py2.7-nspkg.pth
odoo_addons/logistic_requisition_multicurrency/__openerp__.py
odoo_addons/logistic_requisition_multicurrency/__init__.py
odoo_addons/logistic_requisition_multicurrency/README.rst
odoo_addons/logistic_requisition_multicurrency/view/logistic_requisition_line.xml
odoo_addons/logistic_requisition_multicurrency/view/logistic_requisition_source.xml
odoo_addons/logistic_requisition_multicurrency/view/logistic_requisition.xml
odoo_addons/logistic_requisition_multicurrency/i18n/logistic_requisition_multicurrency.pot
odoo_addons/logistic_requisition_multicurrency/model/logistic_requisition.py
odoo_addons/logistic_requisition_multicurrency/model/logistic_requisition_line.py
odoo_addons/logistic_requisition_multicurrency/model/logistic_requisition_source.py
odoo_addons/logistic_requisition_multicurrency/model/__init__.py
odoo8_addon_logistic_requisition_multicurrency-8.0.0.1.1.dist-info/top_level.txt
odoo8_addon_logistic_requisition_multicurrency-8.0.0.1.1.dist-info/WHEEL
odoo8_addon_logistic_requisition_multicurrency-8.0.0.1.1.dist-info/RECORD
odoo8_addon_logistic_requisition_multicurrency-8.0.0.1.1.dist-info/metadata.json
odoo8_addon_logistic_requisition_multicurrency-8.0.0.1.1.dist-info/DESCRIPTION.rst
odoo8_addon_logistic_requisition_multicurrency-8.0.0.1.1.dist-info/METADATA
odoo8_addon_logistic_requisition_multicurrency-8.0.0.1.1.dist-info/namespace_packages.txt
